bas_metadata_library/__init__.py
bas_metadata_library/schemas/dist/iec_pas_61174_0_v1.json
bas_metadata_library/schemas/dist/iec_pas_61174_1_v1.json
bas_metadata_library/schemas/dist/iso_19115_0_v4.json
bas_metadata_library/schemas/dist/iso_19115_2_v4.json
bas_metadata_library/schemas/dist/magic_discovery_v1.json
bas_metadata_library/schemas/src/iec_pas_61174_0_v1.json
bas_metadata_library/schemas/src/iec_pas_61174_1_v1.json
bas_metadata_library/schemas/src/iso_19115_0_v4.json
bas_metadata_library/schemas/src/iso_19115_2_v4.json
bas_metadata_library/schemas/src/magic_discovery_v1.json
bas_metadata_library/schemas/xsd/gco/basicTypes.xsd
bas_metadata_library/schemas/xsd/gco/gco.xsd
bas_metadata_library/schemas/xsd/gco/gcoBase.xsd
bas_metadata_library/schemas/xsd/gmd/applicationSchema.xsd
bas_metadata_library/schemas/xsd/gmd/citation.xsd
bas_metadata_library/schemas/xsd/gmd/constraints.xsd
bas_metadata_library/schemas/xsd/gmd/content.xsd
bas_metadata_library/schemas/xsd/gmd/dataQuality.xsd
bas_metadata_library/schemas/xsd/gmd/distribution.xsd
bas_metadata_library/schemas/xsd/gmd/extent.xsd
bas_metadata_library/schemas/xsd/gmd/freeText.xsd
bas_metadata_library/schemas/xsd/gmd/gmd.xsd
bas_metadata_library/schemas/xsd/gmd/identification.xsd
bas_metadata_library/schemas/xsd/gmd/maintenance.xsd
bas_metadata_library/schemas/xsd/gmd/metadataApplication.xsd
bas_metadata_library/schemas/xsd/gmd/metadataEntity.xsd
bas_metadata_library/schemas/xsd/gmd/metadataExtension.xsd
bas_metadata_library/schemas/xsd/gmd/portrayalCatalogue.xsd
bas_metadata_library/schemas/xsd/gmd/referenceSystem.xsd
bas_metadata_library/schemas/xsd/gmd/spatialRepresentation.xsd
bas_metadata_library/schemas/xsd/gmi/acquisitionInformation.xsd
bas_metadata_library/schemas/xsd/gmi/contentInformation.xsd
bas_metadata_library/schemas/xsd/gmi/dataQualityInformation.xsd
bas_metadata_library/schemas/xsd/gmi/gmi.xsd
bas_metadata_library/schemas/xsd/gmi/metadataEntitySet.xsd
bas_metadata_library-0.15.3.dist-info/LICENSE.md
bas_metadata_library-0.15.3.dist-info/METADATA
bas_metadata_library-0.15.3.dist-info/WHEEL
bas_metadata_library-0.15.3.dist-info/RECORD
