Metadata-Version: 2.1
Name: bas-metadata-library
Version: 0.15.3
Summary: Python library for generating metadata records
Home-page: https://github.com/antarctica/metadata-library
License: MIT
Author: Felix Fennell
Author-email: felnne@bas.ac.uk
Requires-Python: >=3.9,<4.0
Classifier: Development Status :: 5 - Production/Stable
Classifier: Intended Audience :: Developers
Classifier: Intended Audience :: Science/Research
Classifier: License :: OSI Approved :: MIT License
Classifier: Operating System :: OS Independent
Classifier: Programming Language :: Python :: 3
Classifier: Programming Language :: Python :: 3.9
Classifier: Programming Language :: Python :: 3.10
Classifier: Programming Language :: Python :: 3.11
Classifier: Programming Language :: Python :: 3.12
Classifier: Topic :: Software Development :: Libraries
Requires-Dist: importlib-resources (>=6.4.4,<7.0.0)
Requires-Dist: jsonschema (==4.23.0)
Requires-Dist: lxml (>=5.3.0,<6.0.0)
Requires-Dist: rfc3987 (>=1.3.8,<2.0.0)
Requires-Dist: strict-rfc3339 (>=0.7,<0.8)
Project-URL: Repository, https://github.com/antarctica/metadata-library
